{
  "id": "dynamic-pricing-trends",
  "title": "Dynamic Pricing Trends Reshaping E-Commerce in 2026",
  "date": "2026-03-17",
  "author": "Pricing Intelligence",
  "tags": ["dynamic pricing", "e-commerce", "AI"],
  "excerpt": "How real-time pricing algorithms are fundamentally changing how consumers shop — and how brands compete.",
  "content": "Dynamic pricing is no longer a differentiator — it's table stakes. In 2026, more than 70% of major e-commerce players use some form of algorithmic pricing, adjusting prices thousands of times per day based on demand signals, competitor moves, and inventory levels.\n\nThe real battleground has shifted from *whether* to use dynamic pricing to *how intelligently* it's deployed. Early movers who relied on simple rule-based engines are finding themselves undercut by competitors using demand-sensing AI that anticipates price sensitivity at the SKU level.\n\n## What's Changed\n\nThree forces are reshaping the landscape:\n\n**1. Consumer awareness is rising.** Browser extensions that track price history have over 50M installs globally. Shoppers increasingly wait for dips, especially on big-ticket items.\n\n**2. Competitor data is more accessible.** Real-time competitor price monitoring used to require enterprise contracts. Now it's available at SMB price points.\n\n**3. Margin pressure is severe.** With acquisition costs high, brands are using pricing as a margin lever more aggressively than ever.\n\n## What This Means for Your Strategy\n\nThe winners in this environment are doing two things: they're pricing on value signals (not just cost-plus or competitor-minus), and they're using segmentation to protect their best customers from price volatility that erodes trust.\n\nPricing intelligence is no longer a back-office function. It belongs in the room where growth decisions are made."
}
